rasahub_rasa/__init__.py
rasahub_rasa/rasahubchannel.py
rasahub_rasa-0.3.1.dist-info/METADATA
rasahub_rasa-0.3.1.dist-info/RECORD
rasahub_rasa-0.3.1.dist-info/WHEEL
rasahub_rasa-0.3.1.dist-info/top_level.txt
