Metadata-Version: 2.1
Name: rasahub-rasa
Version: 0.3.1
Summary: Rasa connector for Rasahub
Home-page: http://github.com/frommie/rasahub-rasa
Author: Christian Frommert
Author-email: christian.frommert@gmail.com
License: MIT
Keywords: rasahub rasa rasa_core
Platform: UNKNOWN
Classifier: Development Status :: 3 - Alpha
Classifier: Intended Audience :: Developers
Classifier: License :: OSI Approved :: MIT License
Classifier: Programming Language :: Python :: 2.7
Classifier: Topic :: Software Development
Provides-Extra: test
Requires-Dist: rasahub
Requires-Dist: rasa-core
Requires-Dist: rasa-nlu (==0.11.0)
Provides-Extra: test
